llamaline/__init__.py
llamaline/llamaline.py
llamaline-1.0.2.dist-info/METADATA
llamaline-1.0.2.dist-info/WHEEL
llamaline-1.0.2.dist-info/entry_points.txt
llamaline-1.0.2.dist-info/top_level.txt
llamaline-1.0.2.dist-info/RECORD
