Metadata-Version: 2.4
Name: llamaline
Version: 1.0.2
Summary: A natural-language to shell/Python CLI assistant using local Ollama models.
Author-email: Luke Steuber <luke@lukesteuber.com>
License-Expression: MIT
Project-URL: Homepage, https://github.com/lukeslp/llamaline
Project-URL: Documentation, https://github.com/lukeslp/llamaline#readme
Project-URL: Repository, https://github.com/lukeslp/llamaline
Project-URL: Bug Tracker, https://github.com/lukeslp/llamaline/issues
Keywords: cli,natural-language,ollama,accessibility,automation
Classifier: Development Status :: 5 - Production/Stable
Classifier: Intended Audience :: Developers
Classifier: Intended Audience :: System Administrators
Classifier: Operating System :: OS Independent
Classifier: Programming Language :: Python :: 3
Classifier: Programming Language :: Python :: 3.7
Classifier: Programming Language :: Python :: 3.8
Classifier: Programming Language :: Python :: 3.9
Classifier: Programming Language :: Python :: 3.10
Classifier: Programming Language :: Python :: 3.11
Classifier: Programming Language :: Python :: 3.12
Classifier: Topic :: Software Development :: Libraries :: Python Modules
Classifier: Topic :: System :: System Shells
Classifier: Topic :: Utilities
Requires-Python: >=3.7
Requires-Dist: colorama
Requires-Dist: rich
Requires-Dist: requests
